spot_check_files/__init__.py
spot_check_files/__main__.py
spot_check_files/archives.py
spot_check_files/basics.py
spot_check_files/checker.py
spot_check_files/cli.py
spot_check_files/filenames.py
spot_check_files/quicklook.py
spot_check_files/report.py
spot_check_files/_monoid_font/Monoid-Regular.ttf
spot_check_files/_monoid_font/__init__.py
spot_check_files/_templates/__init__.py
spot_check_files/_templates/report.html
spot_check_files-0.0.2.dist-info/LICENSE
spot_check_files-0.0.2.dist-info/METADATA
spot_check_files-0.0.2.dist-info/WHEEL
spot_check_files-0.0.2.dist-info/entry_points.txt
spot_check_files-0.0.2.dist-info/top_level.txt
spot_check_files-0.0.2.dist-info/RECORD
