Metadata-Version: 2.1
Name: spot-check-files
Version: 0.0.2
Summary: Helps validate the integrity of data backups/exports.
Home-page: https://github.com/brokensandals/spot_check_files
Author: Jacob Williams
Author-email: jacobaw@gmail.com
License: UNKNOWN
Platform: UNKNOWN
Classifier: Programming Language :: Python :: 3
Classifier: License :: OSI Approved :: MIT License
Classifier: Operating System :: MacOS :: MacOS X
Requires-Python: >=3.7
Requires-Dist: Jinja2
Requires-Dist: Pillow
Requires-Dist: terminaltables
Provides-Extra: imgcat
Requires-Dist: imgcat ; extra == 'imgcat'
